pythoyo.py
shyell.py
shÿell.py
styings_with_ayyows.py
asyets/__init__.py
asyets/imyages/pythOyO_500px_Logo.png
asyets/imyages/pythOyO_500px_Logo2.png
asyets/imyages/pythOyO_500px_Logo3.png
asyets/imyages/pythOyO_Logo.png
exyamples/__init__.py
exyamples/calcuyulator.pyoyo
exyamples/catayan.pyoyo
test/__init__.py
test/test_stying.py
pythOyO-0.1.0.dist-info/LICENSE
pythOyO-0.1.0.dist-info/METADATA
pythOyO-0.1.0.dist-info/WHEEL
pythOyO-0.1.0.dist-info/top_level.txt
pythOyO-0.1.0.dist-info/RECORD
