Metadata-Version: 2.1
Name: pythOyO
Version: 0.1.0
Summary: A fun and whimsical UyU programming language written in python
Home-page: https://github.com/RajChat-hub/pythOyO
Author: Rajdeep Chatterjee
Author-email: rc9775295@gmail.com
License: UNKNOWN
Platform: UNKNOWN
Classifier: Programming Language :: Python :: 3
Classifier: License :: OSI Approved :: MIT License
Classifier: Operating System :: OS Independent
Requires-Python: >=3.6
License-File: LICENSE
